{
    "key": "group_58092c7f99a7f",
    "title": "About Page Fields",
    "fields": [
        {
            "key": "field_58093aaaa2472",
            "label": "Image landscape",
            "name": "img_land",
            "type": "image",
            "instructions": "",
            "required": 0,
            "conditional_logic": 0,
            "wrapper": {
                "width": "",
                "class": "",
                "id": ""
            },
            "return_format": "array",
            "preview_size": "thumbnail",
            "library": "all",
            "min_width": "",
            "min_height": "",
            "min_size": "",
            "max_width": "",
            "max_height": "",
            "max_size": "",
            "mime_types": ""
        },
        {
            "key": "field_58093ac3a2473",
            "label": "Image Portrait",
            "name": "img_port",
            "type": "image",
            "instructions": "",
            "required": 0,
            "conditional_logic": 0,
            "wrapper": {
                "width": "",
                "class": "",
                "id": ""
            },
            "return_format": "array",
            "preview_size": "thumbnail",
            "library": "all",
            "min_width": "",
            "min_height": "",
            "min_size": "",
            "max_width": "",
            "max_height": "",
            "max_size": "",
            "mime_types": ""
        },
        {
            "key": "field_580935994db4e",
            "label": "Main Heading",
            "name": "heading",
            "type": "text",
            "instructions": "",
            "required": 0,
            "conditional_logic": 0,
            "wrapper": {
                "width": "",
                "class": "",
                "id": ""
            },
            "default_value": "",
            "placeholder": "",
            "prepend": "",
            "append": "",
            "maxlength": ""
        },
        {
            "key": "field_580935b64db4f",
            "label": "Main Content",
            "name": "main_content",
            "type": "wysiwyg",
            "instructions": "",
            "required": 0,
            "conditional_logic": 0,
            "wrapper": {
                "width": "",
                "class": "",
                "id": ""
            },
            "default_value": "",
            "tabs": "all",
            "toolbar": "full",
            "media_upload": 0
        },
        {
            "key": "field_58092c9b5bf8d",
            "label": "Layout Rows",
            "name": "rows",
            "type": "flexible_content",
            "instructions": "",
            "required": 0,
            "conditional_logic": 0,
            "wrapper": {
                "width": "",
                "class": "",
                "id": ""
            },
            "button_label": "Add Row",
            "min": "",
            "max": "",
            "layouts": [
                {
                    "key": "58092eee89ef8",
                    "name": "1column",
                    "label": "One Column",
                    "display": "block",
                    "sub_fields": [
                        {
                            "key": "field_58092f0489ef9",
                            "label": "Type",
                            "name": "type",
                            "type": "select",
                            "instructions": "",
                            "required": 0,
                            "conditional_logic": 0,
                            "wrapper": {
                                "width": "",
                                "class": "",
                                "id": ""
                            },
                            "choices": {
                                "text": "Text",
                                "image": "Image"
                            },
                            "default_value": [],
                            "allow_null": 0,
                            "multiple": 0,
                            "ui": 0,
                            "ajax": 0,
                            "return_format": "value",
                            "placeholder": ""
                        },
                        {
                            "key": "field_58092f2489efa",
                            "label": "Title",
                            "name": "title",
                            "type": "text",
                            "instructions": "",
                            "required": 0,
                            "conditional_logic": [
                                [
                                    {
                                        "field": "field_58092f0489ef9",
                                        "operator": "==",
                                        "value": "text"
                                    }
                                ]
                            ],
                            "wrapper": {
                                "width": "",
                                "class": "",
                                "id": ""
                            },
                            "default_value": "",
                            "placeholder": "",
                            "prepend": "",
                            "append": "",
                            "maxlength": ""
                        },
                        {
                            "key": "field_58092f3689efb",
                            "label": "Text",
                            "name": "text",
                            "type": "wysiwyg",
                            "instructions": "",
                            "required": 0,
                            "conditional_logic": [
                                [
                                    {
                                        "field": "field_58092f0489ef9",
                                        "operator": "==",
                                        "value": "text"
                                    }
                                ]
                            ],
                            "wrapper": {
                                "width": "",
                                "class": "",
                                "id": ""
                            },
                            "default_value": "",
                            "tabs": "all",
                            "toolbar": "full",
                            "media_upload": 0
                        },
                        {
                            "key": "field_58092f4a89efc",
                            "label": "Image",
                            "name": "image",
                            "type": "image",
                            "instructions": "",
                            "required": 0,
                            "conditional_logic": [
                                [
                                    {
                                        "field": "field_58092f0489ef9",
                                        "operator": "==",
                                        "value": "image"
                                    }
                                ]
                            ],
                            "wrapper": {
                                "width": "",
                                "class": "",
                                "id": ""
                            },
                            "return_format": "array",
                            "preview_size": "thumbnail",
                            "library": "all",
                            "min_width": "",
                            "min_height": "",
                            "min_size": "",
                            "max_width": "",
                            "max_height": "",
                            "max_size": "",
                            "mime_types": ""
                        }
                    ],
                    "min": "",
                    "max": ""
                },
                {
                    "key": "58092c9fa99a1",
                    "name": "2col",
                    "label": "Two Column",
                    "display": "block",
                    "sub_fields": [
                        {
                            "key": "field_58092cd05bf8e",
                            "label": "Col 1",
                            "name": "",
                            "type": "tab",
                            "instructions": "",
                            "required": 0,
                            "conditional_logic": 0,
                            "wrapper": {
                                "width": "",
                                "class": "",
                                "id": ""
                            },
                            "placement": "top",
                            "endpoint": 0
                        },
                        {
                            "key": "field_58092cee5bf8f",
                            "label": "Type",
                            "name": "col_1_type",
                            "type": "select",
                            "instructions": "",
                            "required": 0,
                            "conditional_logic": 0,
                            "wrapper": {
                                "width": "",
                                "class": "",
                                "id": ""
                            },
                            "choices": {
                                "text": "Text",
                                "image": "Image"
                            },
                            "default_value": [],
                            "allow_null": 0,
                            "multiple": 0,
                            "ui": 0,
                            "ajax": 0,
                            "return_format": "value",
                            "placeholder": ""
                        },
                        {
                            "key": "field_58092d405bf90",
                            "label": "Title",
                            "name": "col_1_title",
                            "type": "text",
                            "instructions": "",
                            "required": 0,
                            "conditional_logic": [
                                [
                                    {
                                        "field": "field_58092cee5bf8f",
                                        "operator": "==",
                                        "value": "text"
                                    }
                                ]
                            ],
                            "wrapper": {
                                "width": "",
                                "class": "",
                                "id": ""
                            },
                            "default_value": "",
                            "placeholder": "",
                            "prepend": "",
                            "append": "",
                            "maxlength": ""
                        },
                        {
                            "key": "field_58092d9d5bf91",
                            "label": "Text",
                            "name": "col_1_text",
                            "type": "wysiwyg",
                            "instructions": "",
                            "required": "",
                            "conditional_logic": [
                                [
                                    {
                                        "field": "field_58092cee5bf8f",
                                        "operator": "==",
                                        "value": "text"
                                    }
                                ]
                            ],
                            "wrapper": {
                                "width": "",
                                "class": "",
                                "id": ""
                            },
                            "default_value": "",
                            "tabs": "all",
                            "toolbar": "full",
                            "media_upload": 0
                        },
                        {
                            "key": "field_58092dda5bf92",
                            "label": "Image",
                            "name": "col_1_image",
                            "type": "image",
                            "instructions": "",
                            "required": 0,
                            "conditional_logic": [
                                [
                                    {
                                        "field": "field_58092cee5bf8f",
                                        "operator": "==",
                                        "value": "image"
                                    }
                                ]
                            ],
                            "wrapper": {
                                "width": "",
                                "class": "",
                                "id": ""
                            },
                            "return_format": "array",
                            "preview_size": "thumbnail",
                            "library": "all",
                            "min_width": "",
                            "min_height": "",
                            "min_size": "",
                            "max_width": "",
                            "max_height": "",
                            "max_size": "",
                            "mime_types": ""
                        },
                        {
                            "key": "field_58092e415bf95",
                            "label": "Col 2",
                            "name": "",
                            "type": "tab",
                            "instructions": "",
                            "required": 0,
                            "conditional_logic": 0,
                            "wrapper": {
                                "width": "",
                                "class": "",
                                "id": ""
                            },
                            "placement": "top",
                            "endpoint": 0
                        },
                        {
                            "key": "field_58092e56cae39",
                            "label": "Type",
                            "name": "col_2_type",
                            "type": "select",
                            "instructions": "",
                            "required": "",
                            "conditional_logic": "",
                            "wrapper": {
                                "width": "",
                                "class": "",
                                "id": ""
                            },
                            "choices": {
                                "text": "Text",
                                "image": "Image"
                            },
                            "default_value": [],
                            "allow_null": "",
                            "multiple": "",
                            "ui": "",
                            "ajax": "",
                            "return_format": "",
                            "placeholder": ""
                        },
                        {
                            "key": "field_58092e66cae3a",
                            "label": "Title",
                            "name": "col_2_title",
                            "type": "text",
                            "instructions": "",
                            "required": 0,
                            "conditional_logic": [
                                [
                                    {
                                        "field": "field_58092e56cae39",
                                        "operator": "==",
                                        "value": "text"
                                    }
                                ]
                            ],
                            "wrapper": {
                                "width": "",
                                "class": "",
                                "id": ""
                            },
                            "default_value": "",
                            "placeholder": "",
                            "prepend": "",
                            "append": "",
                            "maxlength": ""
                        },
                        {
                            "key": "field_58092e97cae3b",
                            "label": "Text",
                            "name": "col_2_text",
                            "type": "wysiwyg",
                            "instructions": "",
                            "required": "",
                            "conditional_logic": [
                                [
                                    {
                                        "field": "field_58092e56cae39",
                                        "operator": "==",
                                        "value": "text"
                                    }
                                ]
                            ],
                            "wrapper": {
                                "width": "",
                                "class": "",
                                "id": ""
                            },
                            "default_value": "",
                            "tabs": "all",
                            "toolbar": "full",
                            "media_upload": 0
                        },
                        {
                            "key": "field_58092ea6cae3c",
                            "label": "Image",
                            "name": "col_2_image",
                            "type": "image",
                            "instructions": "",
                            "required": 0,
                            "conditional_logic": [
                                [
                                    {
                                        "field": "field_58092e56cae39",
                                        "operator": "==",
                                        "value": "image"
                                    }
                                ]
                            ],
                            "wrapper": {
                                "width": "",
                                "class": "",
                                "id": ""
                            },
                            "return_format": "array",
                            "preview_size": "thumbnail",
                            "library": "all",
                            "min_width": "",
                            "min_height": "",
                            "min_size": "",
                            "max_width": "",
                            "max_height": "",
                            "max_size": "",
                            "mime_types": ""
                        }
                    ],
                    "min": "",
                    "max": ""
                },
                {
                    "key": "58092f8c89efd",
                    "name": "collage_ltlbr",
                    "label": "Collage (large top left and bottom right)",
                    "display": "block",
                    "sub_fields": [
                        {
                            "key": "field_58092f8c89efe",
                            "label": "Col 1 Row 1 (Large)",
                            "name": "",
                            "type": "tab",
                            "instructions": "",
                            "required": 0,
                            "conditional_logic": "",
                            "wrapper": {
                                "width": "",
                                "class": "",
                                "id": ""
                            },
                            "placement": "top",
                            "endpoint": 0
                        },
                        {
                            "key": "field_58092f8c89eff",
                            "label": "Type",
                            "name": "col_1_r1_1_type",
                            "type": "select",
                            "instructions": "",
                            "required": 0,
                            "conditional_logic": "",
                            "wrapper": {
                                "width": "",
                                "class": "",
                                "id": ""
                            },
                            "choices": {
                                "text": "Text",
                                "image": "Image"
                            },
                            "default_value": [],
                            "allow_null": 0,
                            "multiple": 0,
                            "ui": 0,
                            "ajax": 0,
                            "return_format": "value",
                            "placeholder": ""
                        },
                        {
                            "key": "field_58092f8c89f00",
                            "label": "Title",
                            "name": "col_1_r1_1_title",
                            "type": "text",
                            "instructions": "",
                            "required": 0,
                            "conditional_logic": [
                                [
                                    {
                                        "field": "field_58092f8c89eff",
                                        "operator": "==",
                                        "value": "text"
                                    }
                                ]
                            ],
                            "wrapper": {
                                "width": "",
                                "class": "",
                                "id": ""
                            },
                            "default_value": "",
                            "placeholder": "",
                            "prepend": "",
                            "append": "",
                            "maxlength": ""
                        },
                        {
                            "key": "field_58092f8c89f01",
                            "label": "Text",
                            "name": "col_1_r1_1_text",
                            "type": "wysiwyg",
                            "instructions": "",
                            "required": 0,
                            "conditional_logic": [
                                [
                                    {
                                        "field": "field_58092f8c89eff",
                                        "operator": "==",
                                        "value": "text"
                                    }
                                ]
                            ],
                            "wrapper": {
                                "width": "",
                                "class": "",
                                "id": ""
                            },
                            "default_value": "",
                            "tabs": "all",
                            "toolbar": "full",
                            "media_upload": 0
                        },
                        {
                            "key": "field_58092f8c89f02",
                            "label": "Image",
                            "name": "col_1_r1_1_image",
                            "type": "image",
                            "instructions": "",
                            "required": 0,
                            "conditional_logic": [
                                [
                                    {
                                        "field": "field_58092f8c89eff",
                                        "operator": "==",
                                        "value": "image"
                                    }
                                ]
                            ],
                            "wrapper": {
                                "width": "",
                                "class": "",
                                "id": ""
                            },
                            "return_format": "array",
                            "preview_size": "thumbnail",
                            "library": "all",
                            "min_width": "",
                            "min_height": "",
                            "min_size": "",
                            "max_width": "",
                            "max_height": "",
                            "max_size": "",
                            "mime_types": ""
                        },
                        {
                            "key": "field_58092f8c89f03",
                            "label": "Col 1 Row 2 Item 1 (Small)",
                            "name": "",
                            "type": "tab",
                            "instructions": "",
                            "required": 0,
                            "conditional_logic": "",
                            "wrapper": {
                                "width": "",
                                "class": "",
                                "id": ""
                            },
                            "placement": "top",
                            "endpoint": 0
                        },
                        {
                            "key": "field_58092f8c89f04",
                            "label": "Type",
                            "name": "col_1_r2_1_type",
                            "type": "select",
                            "instructions": "",
                            "required": 0,
                            "conditional_logic": "",
                            "wrapper": {
                                "width": "",
                                "class": "",
                                "id": ""
                            },
                            "choices": {
                                "text": "Text",
                                "image": "Image"
                            },
                            "default_value": [],
                            "allow_null": 0,
                            "multiple": 0,
                            "ui": 0,
                            "ajax": 0,
                            "return_format": "value",
                            "placeholder": ""
                        },
                        {
                            "key": "field_58092f8c89f05",
                            "label": "Title",
                            "name": "col_1_r2_1_title",
                            "type": "text",
                            "instructions": "",
                            "required": 0,
                            "conditional_logic": [
                                [
                                    {
                                        "field": "field_58092f8c89f04",
                                        "operator": "==",
                                        "value": "text"
                                    }
                                ]
                            ],
                            "wrapper": {
                                "width": "",
                                "class": "",
                                "id": ""
                            },
                            "default_value": "",
                            "placeholder": "",
                            "prepend": "",
                            "append": "",
                            "maxlength": ""
                        },
                        {
                            "key": "field_58092f8c89f06",
                            "label": "Text",
                            "name": "col_1_r2_1_text",
                            "type": "wysiwyg",
                            "instructions": "",
                            "required": 0,
                            "conditional_logic": [
                                [
                                    {
                                        "field": "field_58092f8c89f04",
                                        "operator": "==",
                                        "value": "text"
                                    }
                                ]
                            ],
                            "wrapper": {
                                "width": "",
                                "class": "",
                                "id": ""
                            },
                            "default_value": "",
                            "tabs": "all",
                            "toolbar": "full",
                            "media_upload": 0
                        },
                        {
                            "key": "field_58092f8c89f07",
                            "label": "Image",
                            "name": "col_1_r2_1_image",
                            "type": "image",
                            "instructions": "",
                            "required": 0,
                            "conditional_logic": [
                                [
                                    {
                                        "field": "field_58092f8c89f04",
                                        "operator": "==",
                                        "value": "image"
                                    }
                                ]
                            ],
                            "wrapper": {
                                "width": "",
                                "class": "",
                                "id": ""
                            },
                            "return_format": "array",
                            "preview_size": "thumbnail",
                            "library": "all",
                            "min_width": "",
                            "min_height": "",
                            "min_size": "",
                            "max_width": "",
                            "max_height": "",
                            "max_size": "",
                            "mime_types": ""
                        },
                        {
                            "key": "field_580930af89f08",
                            "label": "Col 1 Row 2 Item 2 (Small)",
                            "name": "",
                            "type": "tab",
                            "instructions": "",
                            "required": 0,
                            "conditional_logic": "",
                            "wrapper": {
                                "width": "",
                                "class": "",
                                "id": ""
                            },
                            "placement": "top",
                            "endpoint": 0
                        },
                        {
                            "key": "field_580930c189f09",
                            "label": "Type",
                            "name": "col_1_r2_2_type",
                            "type": "select",
                            "instructions": "",
                            "required": 0,
                            "conditional_logic": "",
                            "wrapper": {
                                "width": "",
                                "class": "",
                                "id": ""
                            },
                            "choices": {
                                "text": "Text",
                                "image": "Image"
                            },
                            "default_value": [],
                            "allow_null": 0,
                            "multiple": 0,
                            "ui": 0,
                            "ajax": 0,
                            "return_format": "value",
                            "placeholder": ""
                        },
                        {
                            "key": "field_580930e689f0a",
                            "label": "Title",
                            "name": "col_1_r2_2_title",
                            "type": "text",
                            "instructions": "",
                            "required": 0,
                            "conditional_logic": [
                                [
                                    {
                                        "field": "field_580930c189f09",
                                        "operator": "==",
                                        "value": "text"
                                    }
                                ]
                            ],
                            "wrapper": {
                                "width": "",
                                "class": "",
                                "id": ""
                            },
                            "default_value": "",
                            "placeholder": "",
                            "prepend": "",
                            "append": "",
                            "maxlength": ""
                        },
                        {
                            "key": "field_580930fe89f0b",
                            "label": "Text",
                            "name": "col_1_r2_2_text",
                            "type": "wysiwyg",
                            "instructions": "",
                            "required": 0,
                            "conditional_logic": [
                                [
                                    {
                                        "field": "field_580930c189f09",
                                        "operator": "==",
                                        "value": "text"
                                    }
                                ]
                            ],
                            "wrapper": {
                                "width": "",
                                "class": "",
                                "id": ""
                            },
                            "default_value": "",
                            "tabs": "all",
                            "toolbar": "full",
                            "media_upload": 0
                        },
                        {
                            "key": "field_5809312289f0c",
                            "label": "Image",
                            "name": "col_1_r2_2_image",
                            "type": "image",
                            "instructions": "",
                            "required": 0,
                            "conditional_logic": [
                                [
                                    {
                                        "field": "field_580930c189f09",
                                        "operator": "==",
                                        "value": "image"
                                    }
                                ]
                            ],
                            "wrapper": {
                                "width": "",
                                "class": "",
                                "id": ""
                            },
                            "return_format": "array",
                            "preview_size": "thumbnail",
                            "library": "all",
                            "min_width": "",
                            "min_height": "",
                            "min_size": "",
                            "max_width": "",
                            "max_height": "",
                            "max_size": "",
                            "mime_types": ""
                        },
                        {
                            "key": "field_5809319c89f0e",
                            "label": "Col 2 Row 1 Item 1 (Small)",
                            "name": "",
                            "type": "tab",
                            "instructions": "",
                            "required": 0,
                            "conditional_logic": "",
                            "wrapper": {
                                "width": "",
                                "class": "",
                                "id": ""
                            },
                            "placement": "top",
                            "endpoint": 0
                        },
                        {
                            "key": "field_580931c289f0f",
                            "label": "Type",
                            "name": "col_2_r1_1_type",
                            "type": "select",
                            "instructions": "",
                            "required": 0,
                            "conditional_logic": "",
                            "wrapper": {
                                "width": "",
                                "class": "",
                                "id": ""
                            },
                            "choices": {
                                "text": "Text",
                                "image": "Image"
                            },
                            "default_value": [],
                            "allow_null": 0,
                            "multiple": 0,
                            "ui": 0,
                            "ajax": 0,
                            "return_format": "value",
                            "placeholder": ""
                        },
                        {
                            "key": "field_5809322d89f10",
                            "label": "Title",
                            "name": "col_2_r1_1_title",
                            "type": "text",
                            "instructions": "",
                            "required": 0,
                            "conditional_logic": [
                                [
                                    {
                                        "field": "field_580931c289f0f",
                                        "operator": "==",
                                        "value": "text"
                                    }
                                ]
                            ],
                            "wrapper": {
                                "width": "",
                                "class": "",
                                "id": ""
                            },
                            "default_value": "",
                            "placeholder": "",
                            "prepend": "",
                            "append": "",
                            "maxlength": ""
                        },
                        {
                            "key": "field_5809325289f11",
                            "label": "Text",
                            "name": "col_2_r1_1_text",
                            "type": "wysiwyg",
                            "instructions": "",
                            "required": 0,
                            "conditional_logic": [
                                [
                                    {
                                        "field": "field_580931c289f0f",
                                        "operator": "==",
                                        "value": "text"
                                    }
                                ]
                            ],
                            "wrapper": {
                                "width": "",
                                "class": "",
                                "id": ""
                            },
                            "default_value": "",
                            "tabs": "all",
                            "toolbar": "full",
                            "media_upload": 0
                        },
                        {
                            "key": "field_5809327489f12",
                            "label": "Image",
                            "name": "col_2_r1_1_image",
                            "type": "image",
                            "instructions": "",
                            "required": 0,
                            "conditional_logic": [
                                [
                                    {
                                        "field": "field_580931c289f0f",
                                        "operator": "==",
                                        "value": "image"
                                    }
                                ]
                            ],
                            "wrapper": {
                                "width": "",
                                "class": "",
                                "id": ""
                            },
                            "return_format": "array",
                            "preview_size": "thumbnail",
                            "library": "all",
                            "min_width": "",
                            "min_height": "",
                            "min_size": "",
                            "max_width": "",
                            "max_height": "",
                            "max_size": "",
                            "mime_types": ""
                        },
                        {
                            "key": "field_5809330f89f13",
                            "label": "Col 2 Row 1 Item 2 (Small)",
                            "name": "",
                            "type": "tab",
                            "instructions": "",
                            "required": 0,
                            "conditional_logic": "",
                            "wrapper": {
                                "width": "",
                                "class": "",
                                "id": ""
                            },
                            "placement": "top",
                            "endpoint": 0
                        },
                        {
                            "key": "field_5809335889f16",
                            "label": "Type",
                            "name": "col_2_r1_2_type",
                            "type": "select",
                            "instructions": "",
                            "required": 0,
                            "conditional_logic": "",
                            "wrapper": {
                                "width": "",
                                "class": "",
                                "id": ""
                            },
                            "choices": {
                                "text": "Text",
                                "image": "Image"
                            },
                            "default_value": [],
                            "allow_null": 0,
                            "multiple": 0,
                            "ui": 0,
                            "ajax": 0,
                            "return_format": "value",
                            "placeholder": ""
                        },
                        {
                            "key": "field_5809338189f17",
                            "label": "Title",
                            "name": "col_2_r1_2_title",
                            "type": "text",
                            "instructions": "",
                            "required": 0,
                            "conditional_logic": [
                                [
                                    {
                                        "field": "field_5809335889f16",
                                        "operator": "==",
                                        "value": "text"
                                    }
                                ]
                            ],
                            "wrapper": {
                                "width": "",
                                "class": "",
                                "id": ""
                            },
                            "default_value": "",
                            "placeholder": "",
                            "prepend": "",
                            "append": "",
                            "maxlength": ""
                        },
                        {
                            "key": "field_580933a389f18",
                            "label": "Text",
                            "name": "col_2_r1_2_text",
                            "type": "wysiwyg",
                            "instructions": "",
                            "required": 0,
                            "conditional_logic": [
                                [
                                    {
                                        "field": "field_5809335889f16",
                                        "operator": "==",
                                        "value": "text"
                                    }
                                ]
                            ],
                            "wrapper": {
                                "width": "",
                                "class": "",
                                "id": ""
                            },
                            "default_value": "",
                            "tabs": "all",
                            "toolbar": "full",
                            "media_upload": 0
                        },
                        {
                            "key": "field_580933c089f19",
                            "label": "Image",
                            "name": "col_2_r1_2_image",
                            "type": "image",
                            "instructions": "",
                            "required": 0,
                            "conditional_logic": [
                                [
                                    {
                                        "field": "field_5809335889f16",
                                        "operator": "==",
                                        "value": "image"
                                    }
                                ]
                            ],
                            "wrapper": {
                                "width": "",
                                "class": "",
                                "id": ""
                            },
                            "return_format": "array",
                            "preview_size": "thumbnail",
                            "library": "all",
                            "min_width": "",
                            "min_height": "",
                            "min_size": "",
                            "max_width": "",
                            "max_height": "",
                            "max_size": "",
                            "mime_types": ""
                        },
                        {
                            "key": "field_58093450f6553",
                            "label": "Col 2 Row 2 (Large)",
                            "name": "",
                            "type": "tab",
                            "instructions": "",
                            "required": 0,
                            "conditional_logic": 0,
                            "wrapper": {
                                "width": "",
                                "class": "",
                                "id": ""
                            },
                            "placement": "top",
                            "endpoint": 0
                        },
                        {
                            "key": "field_5809346df6554",
                            "label": "Type",
                            "name": "col_2_r2_type",
                            "type": "select",
                            "instructions": "",
                            "required": 0,
                            "conditional_logic": 0,
                            "wrapper": {
                                "width": "",
                                "class": "",
                                "id": ""
                            },
                            "choices": {
                                "text": "Text",
                                "image": "Image"
                            },
                            "default_value": [],
                            "allow_null": 0,
                            "multiple": 0,
                            "ui": 0,
                            "ajax": 0,
                            "return_format": "value",
                            "placeholder": ""
                        },
                        {
                            "key": "field_580934bcf6556",
                            "label": "Title",
                            "name": "col_2_r2_title",
                            "type": "text",
                            "instructions": "",
                            "required": 0,
                            "conditional_logic": [
                                [
                                    {
                                        "field": "field_5809346df6554",
                                        "operator": "==",
                                        "value": "text"
                                    }
                                ]
                            ],
                            "wrapper": {
                                "width": "",
                                "class": "",
                                "id": ""
                            },
                            "default_value": "",
                            "placeholder": "",
                            "prepend": "",
                            "append": "",
                            "maxlength": ""
                        },
                        {
                            "key": "field_580934daf6557",
                            "label": "Text",
                            "name": "col_2_r2_text",
                            "type": "wysiwyg",
                            "instructions": "",
                            "required": 0,
                            "conditional_logic": [
                                [
                                    {
                                        "field": "field_5809346df6554",
                                        "operator": "==",
                                        "value": "text"
                                    }
                                ]
                            ],
                            "wrapper": {
                                "width": "",
                                "class": "",
                                "id": ""
                            },
                            "default_value": "",
                            "tabs": "all",
                            "toolbar": "full",
                            "media_upload": 0
                        },
                        {
                            "key": "field_580934f1f6558",
                            "label": "Image",
                            "name": "col_2_r2_image",
                            "type": "image",
                            "instructions": "",
                            "required": 0,
                            "conditional_logic": [
                                [
                                    {
                                        "field": "field_5809346df6554",
                                        "operator": "==",
                                        "value": "image"
                                    }
                                ]
                            ],
                            "wrapper": {
                                "width": "",
                                "class": "",
                                "id": ""
                            },
                            "return_format": "array",
                            "preview_size": "thumbnail",
                            "library": "all",
                            "min_width": "",
                            "min_height": "",
                            "min_size": "",
                            "max_width": "",
                            "max_height": "",
                            "max_size": "",
                            "mime_types": ""
                        }
                    ],
                    "min": "",
                    "max": ""
                }
            ]
        }
    ],
    "location": [
        [
            {
                "param": "page_template",
                "operator": "==",
                "value": "page-templates\/about.php"
            }
        ]
    ],
    "menu_order": 0,
    "position": "normal",
    "style": "default",
    "label_placement": "top",
    "instruction_placement": "label",
    "hide_on_screen": [
        "the_content",
        "featured_image"
    ],
    "active": 1,
    "description": "",
    "modified": 1477078321
}